{
    "paper_id": "21d0b509eba48e5636c07eead64b4a2ac06f9fcf",
    "metadata": {
        "title": "Nonlinear Biomedical Physics On managing complex adaptive systems motivated by biosystems application to infections",
        "authors": [
            {
                "first": "A",
                "middle": [
                    "S"
                ],
                "last": "Hegazi",
                "suffix": "",
                "affiliation": {},
                "email": ""
            },
            {
                "first": "A",
                "middle": [
                    "H"
                ],
                "last": "Hashish",
                "suffix": "",
                "affiliation": {},
                "email": ""
            },
            {
                "first": "E",
                "middle": [],
                "last": "Ahmed",
                "suffix": "",
                "affiliation": {},
                "email": ""
            }
        ]
    },
    "abstract": [
        {
            "text": "Many attempts to control Complex adaptive systems (CAS) have failed. Here we try to learn from biosystems to derive some principles for CAS management. An application to managing infections is given.",
            "cite_spans": [],
            "ref_spans": [],
            "section": "Abstract"
        }
    ],
    "body_text": [
        {
            "text": "Complex adaptive systems are special cases of complex systems. They are complex in that they are diverse and made up of multiple interconnected elements and adaptive in that they have the capacity to change and learn from experience.",
            "cite_spans": [],
            "ref_spans": [],
            "section": ""
        },
        {
            "text": "i.1) CAS consists of adaptive (capable of learning) entities. Some properties of such systems cannot be understood just by studying the constituents. They are called emergent properties [3, 4] .",
            "cite_spans": [
                {
                    "start": 186,
                    "end": 189,
                    "text": "[3,",
                    "ref_id": "BIBREF2"
                },
                {
                    "start": 190,
                    "end": 192,
                    "text": "4]",
                    "ref_id": "BIBREF3"
                }
            ],
            "ref_spans": [],
            "section": ""
        },
        {
            "text": "i.2) Examples of CAS include the brain where the emergent property is cognition which is a property of the brain not of individual cells. We propose that IS is a CAS with tolerance as an emergent property since tolerance is a property of IS as a whole not individual B or T or macrophage etc.... cells. In fact almost every biological, social and financial system is a CAS.",
            "cite_spans": [],
            "ref_spans": [],
            "section": ""
        },
        {
            "text": "i.3) Emergent properties imply that reductions approach is not suitable for CAS. Hence these systems have to be studied as a whole in addition to the reductionest approach. It is crucial to see that both approaches complement each other and are not contradictory [5] .",
            "cite_spans": [
                {
                    "start": 263,
                    "end": 266,
                    "text": "[5]",
                    "ref_id": "BIBREF5"
                }
            ],
            "ref_spans": [],
            "section": ""
        },
        {
            "text": "i.4) CAS have some generic properties e.g. they are open (connected to other systems). Interactions in CAS are nonlinear hence long range predictions in CAS are highly unlikely. Typically they have a network (e.g. evolving network) structure. Optimization in such systems is multiobjective. Control of most CAS is difficult, it should be targeted and integrated i.e. using diverse approaches not just one. Most CAS show delay and memory behavior. Spatial effects should not be neglected in many CAS.",
            "cite_spans": [],
            "ref_spans": [],
            "section": ""
        },
        {
            "text": "Most, but not all, CAS are decentralized.",
            "cite_spans": [],
            "ref_spans": [],
            "section": ""
        },
        {
            "text": "i.5) CAS should be studied as a whole in addition to studying its constituents. Hence in vivo experiments are crucial to understand them. i.6) CAS are difficult to control for the following reasons: They are nonlinear. They are open. Delay is a generic property of CAS. Some failure cases in controlling CAS are the Measles-Mumps Rubella (MMR) vaccination and the change of fish type in Lake Victoria [2] . Therefore in the next sections we try to learn from some CAS systems to derive some principles for \"managing\" CAS.",
            "cite_spans": [
                {
                    "start": 401,
                    "end": 404,
                    "text": "[2]",
                    "ref_id": "BIBREF1"
                }
            ],
            "ref_spans": [],
            "section": ""
        },
        {
            "text": "By management we mean taking decisions with as least bad side effects as possible. And if bad side effects occurred then decisions are taken to remove or contain them as best as possible.",
            "cite_spans": [],
            "ref_spans": [],
            "section": ""
        },
        {
            "text": "Some of the basic concepts for optimization in CAS are:",
            "cite_spans": [],
            "ref_spans": [],
            "section": "Optimization in Complex adaptive systems"
        },
        {
            "text": "ii.1) Multi-objective optimization [6] especially metaheuristics i.e. methods which contain random element and which give a good approximate solution to the optimization problem within a reasonable time.",
            "cite_spans": [
                {
                    "start": 35,
                    "end": 38,
                    "text": "[6]",
                    "ref_id": "BIBREF6"
                }
            ],
            "ref_spans": [],
            "section": "Optimization in Complex adaptive systems"
        },
        {
            "text": "ii.2) Game theory specially evolutionary game theory [7] . In some cases it is important to include the evolution of strategies or players c.f. the immune system deals with almost continuously evolving antigen e.g. bacteria, viruses or macroparasites.",
            "cite_spans": [
                {
                    "start": 53,
                    "end": 56,
                    "text": "[7]",
                    "ref_id": "BIBREF7"
                }
            ],
            "ref_spans": [],
            "section": "Optimization in Complex adaptive systems"
        },
        {
            "text": "ii.3) Fractals and networks which play a crucial role in nonlocal spread of effects e.g. infections.",
            "cite_spans": [],
            "ref_spans": [],
            "section": "Optimization in Complex adaptive systems"
        },
        {
            "text": "ii.4) Collective animal behavior. Some of its principles include [8] : Non-selfish key individuals, positive and negative feed back, diversity and threshold responses.",
            "cite_spans": [
                {
                    "start": 65,
                    "end": 68,
                    "text": "[8]",
                    "ref_id": "BIBREF8"
                }
            ],
            "ref_spans": [],
            "section": "Optimization in Complex adaptive systems"
        },
        {
            "text": "From the above results we conclude the following:",
            "cite_spans": [],
            "ref_spans": [],
            "section": "Conclusions and application to infection"
        },
        {
            "text": "iii.1) CAS are extremely difficult to control hence managing CAS may be a more feasible goal than controlling them.",
            "cite_spans": [],
            "ref_spans": [],
            "section": "Conclusions and application to infection"
        },
        {
            "text": "iii.2) Diverse and integrated approaches to the problem are crucial. In may cases single approaches to the problem may lead to counter-productive results. Also this increases the robustness of the management.",
            "cite_spans": [],
            "ref_spans": [],
            "section": "Conclusions and application to infection"
        },
        {
            "text": "iii.",
            "cite_spans": [],
            "ref_spans": [],
            "section": "Conclusions and application to infection"
        },
        {
            "text": "3) The existence of non-selfish key individuals is necessary to solve many problems.",
            "cite_spans": [],
            "ref_spans": [],
            "section": "Conclusions and application to infection"
        },
        {
            "text": "iii.4) The goals should be multi-objective and only guide lines (metaheuristic) approaches should be adopted. One cannot attempt exact determination or control in nonlinear and open systems. Hence no detailed plans should be laid out, instead guide lines may be more realistic.",
            "cite_spans": [],
            "ref_spans": [],
            "section": "Conclusions and application to infection"
        },
        {
            "text": "iii.5) Small world network structure should be followed hence a kind of hierarchical network with short cuts can significantly improve the efficiency of the system [9] .",
            "cite_spans": [
                {
                    "start": 164,
                    "end": 167,
                    "text": "[9]",
                    "ref_id": "BIBREF9"
                }
            ],
            "ref_spans": [],
            "section": "Conclusions and application to infection"
        },
        {
            "text": "iii.6) Feedback hence adaptive management is expected to be more efficient than decisions taken once and for all. Also considering the system as game theory with evolving strategies or opponents may help.",
            "cite_spans": [],
            "ref_spans": [],
            "section": "Conclusions and application to infection"
        },
        {
            "text": "iii.7) Emergent problems \"messes\" happen and will happen. Now the above conclusions are applied to an overview of infection management. We propose to call such problems \"emergent problems\" [10] . An emergent problem is characterized by:",
            "cite_spans": [
                {
                    "start": 189,
                    "end": 193,
                    "text": "[10]",
                    "ref_id": "BIBREF10"
                }
            ],
            "ref_spans": [],
            "section": "Conclusions and application to infection"
        },
        {
            "text": "1) It has several reasons not just one.",
            "cite_spans": [],
            "ref_spans": [],
            "section": "Conclusions and application to infection"
        },
        {
            "text": "2) It cannot be solved locally (e.g. by one country) hence \"collective efforts\" are needed.",
            "cite_spans": [],
            "ref_spans": [],
            "section": "Conclusions and application to infection"
        },
        {
            "text": "3) It needs a long time to be solved hence evolution in solution strategies has to be taken into consideration.",
            "cite_spans": [],
            "ref_spans": [],
            "section": "Conclusions and application to infection"
        },
        {
            "text": "Collective efforts needed to solve such emergent problems require large scale cooperation. Humans are known not to be good in cooperation. In fact a core problem in most of the above problems is the tragedy of commons [11] which simply states that in the case of finite resources e.g. drugs (which is always the case) a conflict exists between individual's interest and the group's (common) interest e.g. rich and poorer countries. However it is known that for such cooperation to exist a feeling of imminent danger has to exist [12].",
            "cite_spans": [
                {
                    "start": 218,
                    "end": 222,
                    "text": "[11]",
                    "ref_id": "BIBREF11"
                }
            ],
            "ref_spans": [],
            "section": "Conclusions and application to infection"
        },
        {
            "text": "Therefore early preparations to deal with such problems are not expected to be as efficient as should be.",
            "cite_spans": [],
            "ref_spans": [],
            "section": "Conclusions and application to infection"
        },
        {
            "text": "It is clear that the absence of non-selfish key individuals is a key reason for the inability to solve this problem.",
            "cite_spans": [],
            "ref_spans": [],
            "section": "Conclusions and application to infection"
        },
        {
            "text": "However some clusters of cooperators do exist. This should be accompanied by retaliation against non-cooperators to lower their benefits from defection (c.f. prisoner's dilemma game [7] ). Some benefits from our discussion are: i) Diverse approaches to the problem is highly desirable e.g. using multi-drugs to reduce the danger of drug resistance (c.f. the sole dependence on Tami flu for avian influenza).",
            "cite_spans": [
                {
                    "start": 182,
                    "end": 185,
                    "text": "[7]",
                    "ref_id": "BIBREF7"
                }
            ],
            "ref_spans": [],
            "section": "Conclusions and application to infection"
        },
        {
            "text": "ii) The network (long range) effects are crucial in many infections e.g. foot and mouth disease, SARS, Avian flu and H1N1 flu.",
            "cite_spans": [],
            "ref_spans": [],
            "section": "Conclusions and application to infection"
        },
        {
            "text": "iii) We should take into account the evolution of antigens (c.f. the new strains of Tuberculosis).",
            "cite_spans": [],
            "ref_spans": [],
            "section": "Conclusions and application to infection"
        }
    ],
    "bib_entries": {
        "BIBREF0": {
            "ref_id": "b0",
            "title": "Complex systems",
            "authors": [
                {
                    "first": "J",
                    "middle": [
                        "B"
                    ],
                    "last": "Smith",
                    "suffix": ""
                }
            ],
            "year": 2003,
            "venue": "",
            "volume": "",
            "issn": "",
            "pages": "",
            "other_ids": {}
        },
        "BIBREF1": {
            "ref_id": "b1",
            "title": "An Overview of Complex adaptive systems",
            "authors": [
                {
                    "first": "E",
                    "middle": [],
                    "last": "Ahmed",
                    "suffix": ""
                },
                {
                    "first": "A",
                    "middle": [
                        "S"
                    ],
                    "last": "Elgazzar",
                    "suffix": ""
                },
                {
                    "first": "A",
                    "middle": [
                        "S"
                    ],
                    "last": "Hegazi",
                    "suffix": ""
                }
            ],
            "year": null,
            "venue": "MJM 2005, 1:26. 0506059 ArXiv Nonlin",
            "volume": "",
            "issn": "",
            "pages": "",
            "other_ids": {}
        },
        "BIBREF2": {
            "ref_id": "b2",
            "title": "On modelling the immune system as a complex system",
            "authors": [
                {
                    "first": "E",
                    "middle": [],
                    "last": "Ahmed",
                    "suffix": ""
                },
                {
                    "first": "A",
                    "middle": [
                        "H"
                    ],
                    "last": "Hashish",
                    "suffix": ""
                }
            ],
            "year": 2006,
            "venue": "Theory in Biosciences",
            "volume": "124",
            "issn": "2/3",
            "pages": "413--418",
            "other_ids": {}
        },
        "BIBREF3": {
            "ref_id": "b3",
            "title": "Comments on introducing the immune system",
            "authors": [
                {
                    "first": "E",
                    "middle": [],
                    "last": "Ahmed",
                    "suffix": ""
                }
            ],
            "year": null,
            "venue": "",
            "volume": "",
            "issn": "",
            "pages": "",
            "other_ids": {}
        },
        "BIBREF5": {
            "ref_id": "b5",
            "title": "Erdi P: Complexity explained",
            "authors": [],
            "year": 2008,
            "venue": "",
            "volume": "",
            "issn": "",
            "pages": "",
            "other_ids": {}
        },
        "BIBREF6": {
            "ref_id": "b6",
            "title": "Ehrgott M: Multicriteria Optimization",
            "authors": [],
            "year": 2005,
            "venue": "",
            "volume": "",
            "issn": "",
            "pages": "",
            "other_ids": {}
        },
        "BIBREF7": {
            "ref_id": "b7",
            "title": "Game theory",
            "authors": [
                {
                    "first": "J",
                    "middle": [],
                    "last": "Webb",
                    "suffix": ""
                }
            ],
            "year": 2007,
            "venue": "",
            "volume": "",
            "issn": "",
            "pages": "",
            "other_ids": {}
        },
        "BIBREF8": {
            "ref_id": "b8",
            "title": "Sumpter DJT: the principles of collective animal behavior",
            "authors": [],
            "year": null,
            "venue": "Phil Trans R Soc B",
            "volume": "",
            "issn": "",
            "pages": "5--22",
            "other_ids": {}
        },
        "BIBREF9": {
            "ref_id": "b9",
            "title": "Managing complexity",
            "authors": [
                {
                    "first": "D",
                    "middle": [],
                    "last": "Helbing",
                    "suffix": ""
                }
            ],
            "year": 2008,
            "venue": "",
            "volume": "",
            "issn": "",
            "pages": "",
            "other_ids": {}
        },
        "BIBREF10": {
            "ref_id": "b10",
            "title": "Global crisis from complex adaptive systems perspective",
            "authors": [
                {
                    "first": "E",
                    "middle": [],
                    "last": "Ahmed",
                    "suffix": ""
                },
                {
                    "first": "A",
                    "middle": [
                        "S"
                    ],
                    "last": "Hegazi",
                    "suffix": ""
                }
            ],
            "year": 2009,
            "venue": "",
            "volume": "",
            "issn": "",
            "pages": "",
            "other_ids": {}
        },
        "BIBREF11": {
            "ref_id": "b11",
            "title": "Wikipedia article 12. Dreber A, Nowak MA: Gambling for global goods",
            "authors": [],
            "year": 2008,
            "venue": "",
            "volume": "105",
            "issn": "",
            "pages": "2261--2262",
            "other_ids": {}
        }
    },
    "ref_entries": {},
    "back_matter": [
        {
            "text": "One of us (A.S.Hegazi) wishes to thank Mansoura University for its grant which he has used in this research.",
            "cite_spans": [],
            "ref_spans": [],
            "section": "Acknowledgements"
        },
        {
            "text": "The authors declare that they have no competing interests.Publish with Bio Med Central and every scientist can read your work free of charge http://www.nonlinearbiomedphys.com/content/3/1/11",
            "cite_spans": [],
            "ref_spans": [],
            "section": "Competing interests"
        },
        {
            "text": "All three authors contributed equally to this article. All authors read and approved the final manuscript.",
            "cite_spans": [],
            "ref_spans": [],
            "section": "Authors' contributions"
        }
    ]
}